MANIFEST.in
README.rst
setup.py
detective/__init__.py
detective/admin.py
detective/middleware.py
detective/models.py
detective/settings.py
detective/urls.py
detective/views.py
detective/migrations/0001_initial.py
detective/migrations/0002_auto_20150812_1350.py
detective/migrations/0003_auto_20160105_1200.py
detective/migrations/0004_auto_20160105_1224.py
detective/migrations/__init__.py
detective/south_migrations/__init__.py
django_detective.egg-info/PKG-INFO
django_detective.egg-info/SOURCES.txt
django_detective.egg-info/dependency_links.txt
django_detective.egg-info/requires.txt
django_detective.egg-info/top_level.txt