Metadata-Version: 1.1
Name: django-detective
Version: 0.6.3
Summary: Django app that tracks all user requests.
Home-page: https://github.com/PragmaticMates/django-detective
Author: Pragmatic Mates
Author-email: info@pragmaticmates.com
License: GPL License
Keywords: django track activity requests detective
Platform: UNKNOWN
Classifier: Programming Language :: Python
Classifier: Programming Language :: Python :: 2.5
Classifier: Programming Language :: Python :: 2.6
Classifier: Programming Language :: Python :: 2.7
Classifier: Operating System :: OS Independent
Classifier: Environment :: Web Environment
Classifier: Intended Audience :: Developers
Classifier: Framework :: Django
Classifier: License :: OSI Approved :: BSD License
Classifier: Development Status :: 3 - Alpha
